eth_typeshed/__init__.py
eth_typeshed/constants.py
eth_typeshed/multicall.py
eth_typeshed/py.typed
eth_typeshed/aerodrome/__init__.py
eth_typeshed/aerodrome/slipstream.py
eth_typeshed/camelot_v3/__init__.py
eth_typeshed/camelot_v3/factory.py
eth_typeshed/camelot_v3/pool.py
eth_typeshed/chainlink/eth_usd_feed.py
eth_typeshed/dexs/lynex/__init__.py
eth_typeshed/dexs/lynex/router.py
eth_typeshed/erc20/__init__.py
eth_typeshed/erc20/constants.py
eth_typeshed/erc20/erc20.py
eth_typeshed/erc20/events.py
eth_typeshed/erc20/types.py
eth_typeshed/erc4626/__init__.py
eth_typeshed/erc4626/erc4626.py
eth_typeshed/orbiter/__init__.py
eth_typeshed/peapods/__init__.py
eth_typeshed/peapods/index_manager.py
eth_typeshed/peapods/router.py
eth_typeshed/peapods/staking_pool.py
eth_typeshed/peapods/token_rewards.py
eth_typeshed/peapods/weighted_index.py
eth_typeshed/peapods/events/__init__.py
eth_typeshed/peapods/events/index_manager.py
eth_typeshed/peapods/events/peas_protocol_fee.py
eth_typeshed/peapods/events/staking_pool.py
eth_typeshed/peapods/events/token_rewards.py
eth_typeshed/peapods/events/weighted_index.py
eth_typeshed/simulacrum/__init__.py
eth_typeshed/simulacrum/account_manager.py
eth_typeshed/simulacrum/blocks.py
eth_typeshed/simulacrum/command_tracker.py
eth_typeshed/simulacrum/mempool.py
eth_typeshed/simulacrum/registry.py
eth_typeshed/simulacrum/executor/__init__.py
eth_typeshed/simulacrum/executor/executor.py
eth_typeshed/simulacrum/executor/util.py
eth_typeshed/simulacrum/helpers/__init__.py
eth_typeshed/simulacrum/helpers/token_registry.py
eth_typeshed/simulacrum/oracle/__init__.py
eth_typeshed/simulacrum/oracle/registry.py
eth_typeshed/simulacrum/oracle/verifier.py
eth_typeshed/simulacrum/sources/__init__.py
eth_typeshed/simulacrum/sources/command.py
eth_typeshed/simulacrum/sources/twitter.py
eth_typeshed/simulacrum/sources/xsource.py
eth_typeshed/simulacrum/utils/__init__.py
eth_typeshed/simulacrum/utils/base_source.py
eth_typeshed/simulacrum/utils/command.py
eth_typeshed_py-0.1.34.dist-info/METADATA
eth_typeshed_py-0.1.34.dist-info/WHEEL
eth_typeshed_py-0.1.34.dist-info/top_level.txt
eth_typeshed_py-0.1.34.dist-info/RECORD
