Metadata-Version: 2.4
Name: eth-typeshed-py
Version: 0.1.34
Requires-Python: >=3.10
Requires-Dist: eth_rpc_py
Provides-Extra: test
Requires-Dist: pytest==8.3.2; extra == "test"
Requires-Dist: pytest-asyncio==0.24.0; extra == "test"
Requires-Dist: pytest-cov==5.0.0; extra == "test"
Requires-Dist: coverage[toml]==7.3.1; extra == "test"
Provides-Extra: build
Requires-Dist: build[virtualenv]==1.0.3; extra == "build"
Provides-Extra: dev
Requires-Dist: tox; extra == "dev"
Requires-Dist: eth-typeshed-py[lint]; extra == "dev"
Requires-Dist: eth-typeshed-py[test]; extra == "dev"
Requires-Dist: eth-typeshed-py[build]; extra == "dev"
